{
 "appData":{
  "bvmt":{
   "default-vol-string-lang":"bo",
   "metadata-for-bvmt-ver":"0.1.0"
  }
 },
 "attribution":[
  {
   "@language":"en",
   "@value":"Data provided by Esukhia under the CC0 license"
  }
 ],
 "changes":[
  {
   "message":{
    "@language":"en",
    "@value":"migration from rKTs data"
   },
   "time":"2020-10-03T11:35:30Z",
   "user":"bdu:U1653882847"
  }
 ],
 "default-view":"view1",
 "imggroup":"bdr:I1440",
 "pagination":[
  {
   "id":"pgfolios",
   "type":"folios"
  }
 ],
 "spec-version":"0.1.0",
 "status":"released",
 "view":{
  "view1":{
   "imagelist":[
    {
     "filename":"14400001.tif",
     "hidden":true,
     "tags":[
      "T0005"
     ]
    },
    {
     "filename":"14400002.tif",
     "hidden":true,
     "tags":[
      "T0005"
     ]
    },
    {
     "filename":"14400003.tif",
     "hidden":true,
     "tags":[
      "T0005"
     ]
    },
    {
     "filename":"14400004.tif",
     "pagination":{
      "pgfolios":{
       "value":"1b"
      }
     }
    },
    {
     "filename":"14400005.tif",
     "pagination":{
      "pgfolios":{
       "value":"2a"
      }
     }
    },
    {
     "filename":"14400006.tif",
     "pagination":{
      "pgfolios":{
       "value":"2b"
      }
     }
    },
    {
     "filename":"14400007.tif",
     "pagination":{
      "pgfolios":{
       "value":"3a"
      }
     }
    },
    {
     "filename":"14400008.tif",
     "pagination":{
      "pgfolios":{
       "value":"3b"
      }
     }
    },
    {
     "filename":"14400009.tif",
     "pagination":{
      "pgfolios":{
       "value":"4a"
      }
     }
    },
    {
     "filename":"14400010.tif",
     "pagination":{
      "pgfolios":{
       "value":"4b"
      }
     }
    },
    {
     "filename":"14400011.tif",
     "pagination":{
      "pgfolios":{
       "value":"5a"
      }
     }
    },
    {
     "filename":"14400012.tif",
     "pagination":{
      "pgfolios":{
       "value":"5b"
      }
     }
    },
    {
     "filename":"14400013.tif",
     "pagination":{
      "pgfolios":{
       "value":"6a"
      }
     }
    },
    {
     "filename":"14400014.tif",
     "pagination":{
      "pgfolios":{
       "value":"6b"
      }
     }
    },
    {
     "filename":"14400015.tif",
     "pagination":{
      "pgfolios":{
       "value":"7a"
      }
     }
    },
    {
     "filename":"14400016.tif",
     "pagination":{
      "pgfolios":{
       "value":"7b"
      }
     }
    },
    {
     "filename":"14400017.tif",
     "pagination":{
      "pgfolios":{
       "value":"8a"
      }
     }
    },
    {
     "filename":"14400018.tif",
     "pagination":{
      "pgfolios":{
       "value":"8b"
      }
     }
    },
    {
     "filename":"14400019.tif",
     "pagination":{
      "pgfolios":{
       "value":"9a"
      }
     }
    },
    {
     "filename":"14400020.tif",
     "pagination":{
      "pgfolios":{
       "value":"9b"
      }
     }
    },
    {
     "filename":"14400021.tif",
     "pagination":{
      "pgfolios":{
       "value":"10a"
      }
     }
    },
    {
     "filename":"14400022.tif",
     "pagination":{
      "pgfolios":{
       "value":"10b"
      }
     }
    },
    {
     "filename":"14400023.tif",
     "pagination":{
      "pgfolios":{
       "value":"11a"
      }
     }
    },
    {
     "filename":"14400024.tif",
     "pagination":{
      "pgfolios":{
       "value":"11b"
      }
     }
    },
    {
     "filename":"14400025.tif",
     "pagination":{
      "pgfolios":{
       "value":"12a"
      }
     }
    },
    {
     "filename":"14400026.tif",
     "pagination":{
      "pgfolios":{
       "value":"12b"
      }
     }
    },
    {
     "filename":"14400027.tif",
     "pagination":{
      "pgfolios":{
       "value":"13a"
      }
     }
    },
    {
     "filename":"14400028.tif",
     "pagination":{
      "pgfolios":{
       "value":"13b"
      }
     }
    },
    {
     "filename":"14400029.tif",
     "pagination":{
      "pgfolios":{
       "value":"14a"
      }
     }
    },
    {
     "filename":"14400030.tif",
     "pagination":{
      "pgfolios":{
       "value":"14b"
      }
     }
    },
    {
     "filename":"14400031.tif",
     "pagination":{
      "pgfolios":{
       "value":"15a"
      }
     }
    },
    {
     "filename":"14400032.tif",
     "pagination":{
      "pgfolios":{
       "value":"15b"
      }
     }
    },
    {
     "filename":"14400033.tif",
     "pagination":{
      "pgfolios":{
       "value":"16a"
      }
     }
    },
    {
     "filename":"14400034.tif",
     "pagination":{
      "pgfolios":{
       "value":"16b"
      }
     }
    },
    {
     "filename":"14400035.tif",
     "pagination":{
      "pgfolios":{
       "value":"17a"
      }
     }
    },
    {
     "filename":"14400036.tif",
     "pagination":{
      "pgfolios":{
       "value":"17b"
      }
     }
    },
    {
     "filename":"14400037.tif",
     "pagination":{
      "pgfolios":{
       "value":"18a"
      }
     }
    },
    {
     "filename":"14400038.tif",
     "pagination":{
      "pgfolios":{
       "value":"18b"
      }
     }
    },
    {
     "filename":"14400039.tif",
     "pagination":{
      "pgfolios":{
       "value":"19a"
      }
     }
    },
    {
     "filename":"14400040.tif",
     "pagination":{
      "pgfolios":{
       "value":"19b"
      }
     }
    },
    {
     "filename":"14400041.tif",
     "pagination":{
      "pgfolios":{
       "value":"20a"
      }
     }
    },
    {
     "filename":"14400042.tif",
     "pagination":{
      "pgfolios":{
       "value":"20b"
      }
     }
    },
    {
     "filename":"14400043.tif",
     "pagination":{
      "pgfolios":{
       "value":"21a"
      }
     }
    },
    {
     "filename":"14400044.tif",
     "pagination":{
      "pgfolios":{
       "value":"21b"
      }
     }
    },
    {
     "filename":"14400045.tif",
     "pagination":{
      "pgfolios":{
       "value":"22a"
      }
     }
    },
    {
     "filename":"14400046.tif",
     "pagination":{
      "pgfolios":{
       "value":"22b"
      }
     }
    },
    {
     "filename":"14400047.tif",
     "pagination":{
      "pgfolios":{
       "value":"23a"
      }
     }
    },
    {
     "filename":"14400048.tif",
     "pagination":{
      "pgfolios":{
       "value":"23b"
      }
     }
    },
    {
     "filename":"14400049.tif",
     "pagination":{
      "pgfolios":{
       "value":"24a"
      }
     }
    },
    {
     "filename":"14400050.tif",
     "pagination":{
      "pgfolios":{
       "value":"24b"
      }
     }
    },
    {
     "filename":"14400051.tif",
     "pagination":{
      "pgfolios":{
       "value":"25a"
      }
     }
    },
    {
     "filename":"14400052.tif",
     "pagination":{
      "pgfolios":{
       "value":"25b"
      }
     }
    },
    {
     "filename":"14400053.tif",
     "pagination":{
      "pgfolios":{
       "value":"26a"
      }
     }
    },
    {
     "filename":"14400054.tif",
     "pagination":{
      "pgfolios":{
       "value":"26b"
      }
     }
    },
    {
     "filename":"14400055.tif",
     "pagination":{
      "pgfolios":{
       "value":"27a"
      }
     }
    },
    {
     "filename":"14400056.tif",
     "pagination":{
      "pgfolios":{
       "value":"27b"
      }
     }
    },
    {
     "filename":"14400057.tif",
     "pagination":{
      "pgfolios":{
       "value":"28a"
      }
     }
    },
    {
     "filename":"14400058.tif",
     "pagination":{
      "pgfolios":{
       "value":"28b"
      }
     }
    },
    {
     "filename":"14400059.tif",
     "pagination":{
      "pgfolios":{
       "value":"29a"
      }
     }
    },
    {
     "filename":"14400060.tif",
     "pagination":{
      "pgfolios":{
       "value":"29b"
      }
     }
    },
    {
     "filename":"14400061.tif",
     "pagination":{
      "pgfolios":{
       "value":"30a"
      }
     }
    },
    {
     "filename":"14400062.tif",
     "pagination":{
      "pgfolios":{
       "value":"30b"
      }
     }
    },
    {
     "filename":"14400063.tif",
     "pagination":{
      "pgfolios":{
       "value":"31a"
      }
     }
    },
    {
     "filename":"14400064.tif",
     "pagination":{
      "pgfolios":{
       "value":"31b"
      }
     }
    },
    {
     "filename":"14400065.tif",
     "pagination":{
      "pgfolios":{
       "value":"32a"
      }
     }
    },
    {
     "filename":"14400066.tif",
     "pagination":{
      "pgfolios":{
       "value":"32b"
      }
     }
    },
    {
     "filename":"14400067.tif",
     "pagination":{
      "pgfolios":{
       "value":"33a"
      }
     }
    },
    {
     "filename":"14400068.tif",
     "pagination":{
      "pgfolios":{
       "value":"33b"
      }
     }
    },
    {
     "filename":"14400069.tif",
     "pagination":{
      "pgfolios":{
       "value":"34a"
      }
     }
    },
    {
     "filename":"14400070.tif",
     "pagination":{
      "pgfolios":{
       "value":"34b"
      }
     }
    },
    {
     "filename":"14400071.tif",
     "pagination":{
      "pgfolios":{
       "value":"35a"
      }
     }
    },
    {
     "filename":"14400072.tif",
     "pagination":{
      "pgfolios":{
       "value":"35b"
      }
     }
    },
    {
     "filename":"14400073.tif",
     "pagination":{
      "pgfolios":{
       "value":"36a"
      }
     }
    },
    {
     "filename":"14400074.tif",
     "pagination":{
      "pgfolios":{
       "value":"36b"
      }
     }
    },
    {
     "filename":"14400075.tif",
     "pagination":{
      "pgfolios":{
       "value":"37a"
      }
     }
    },
    {
     "filename":"14400076.tif",
     "pagination":{
      "pgfolios":{
       "value":"37b"
      }
     }
    },
    {
     "filename":"14400077.tif",
     "pagination":{
      "pgfolios":{
       "value":"38a"
      }
     }
    },
    {
     "filename":"14400078.tif",
     "pagination":{
      "pgfolios":{
       "value":"38b"
      }
     }
    },
    {
     "filename":"14400079.tif",
     "pagination":{
      "pgfolios":{
       "value":"39a"
      }
     }
    },
    {
     "filename":"14400080.tif",
     "pagination":{
      "pgfolios":{
       "value":"39b"
      }
     }
    },
    {
     "filename":"14400081.tif",
     "pagination":{
      "pgfolios":{
       "value":"40a"
      }
     }
    },
    {
     "filename":"14400082.tif",
     "pagination":{
      "pgfolios":{
       "value":"40b"
      }
     }
    },
    {
     "filename":"14400083.tif",
     "pagination":{
      "pgfolios":{
       "value":"41a"
      }
     }
    },
    {
     "filename":"14400084.tif",
     "pagination":{
      "pgfolios":{
       "value":"41b"
      }
     }
    },
    {
     "filename":"14400085.tif",
     "pagination":{
      "pgfolios":{
       "value":"42a"
      }
     }
    },
    {
     "filename":"14400086.tif",
     "pagination":{
      "pgfolios":{
       "value":"42b"
      }
     }
    },
    {
     "filename":"14400087.tif",
     "pagination":{
      "pgfolios":{
       "value":"43a"
      }
     }
    },
    {
     "filename":"14400088.tif",
     "pagination":{
      "pgfolios":{
       "value":"43b"
      }
     }
    },
    {
     "filename":"14400089.tif",
     "pagination":{
      "pgfolios":{
       "value":"44a"
      }
     }
    },
    {
     "filename":"14400090.tif",
     "pagination":{
      "pgfolios":{
       "value":"44b"
      }
     }
    },
    {
     "filename":"14400091.tif",
     "pagination":{
      "pgfolios":{
       "value":"45a"
      }
     }
    },
    {
     "filename":"14400092.tif",
     "pagination":{
      "pgfolios":{
       "value":"45b"
      }
     }
    },
    {
     "filename":"14400093.tif",
     "pagination":{
      "pgfolios":{
       "value":"46a"
      }
     }
    },
    {
     "filename":"14400094.tif",
     "pagination":{
      "pgfolios":{
       "value":"46b"
      }
     }
    },
    {
     "filename":"14400095.tif",
     "pagination":{
      "pgfolios":{
       "value":"47a"
      }
     }
    },
    {
     "filename":"14400096.tif",
     "pagination":{
      "pgfolios":{
       "value":"47b"
      }
     }
    },
    {
     "filename":"14400097.tif",
     "pagination":{
      "pgfolios":{
       "value":"48a"
      }
     }
    },
    {
     "filename":"14400098.tif",
     "pagination":{
      "pgfolios":{
       "value":"48b"
      }
     }
    },
    {
     "filename":"14400099.tif",
     "pagination":{
      "pgfolios":{
       "value":"49a"
      }
     }
    },
    {
     "filename":"14400100.tif",
     "pagination":{
      "pgfolios":{
       "value":"49b"
      }
     }
    },
    {
     "filename":"14400101.tif",
     "pagination":{
      "pgfolios":{
       "value":"50a"
      }
     }
    },
    {
     "filename":"14400102.tif",
     "pagination":{
      "pgfolios":{
       "value":"50b"
      }
     }
    },
    {
     "filename":"14400103.tif",
     "pagination":{
      "pgfolios":{
       "value":"51a"
      }
     }
    },
    {
     "filename":"14400104.tif",
     "pagination":{
      "pgfolios":{
       "value":"51b"
      }
     }
    },
    {
     "filename":"14400105.tif",
     "pagination":{
      "pgfolios":{
       "value":"52a"
      }
     }
    },
    {
     "filename":"14400106.tif",
     "pagination":{
      "pgfolios":{
       "value":"52b"
      }
     }
    },
    {
     "filename":"14400107.tif",
     "pagination":{
      "pgfolios":{
       "value":"53a"
      }
     }
    },
    {
     "filename":"14400108.tif",
     "pagination":{
      "pgfolios":{
       "value":"53b"
      }
     }
    },
    {
     "filename":"14400109.tif",
     "pagination":{
      "pgfolios":{
       "value":"54a"
      }
     }
    },
    {
     "filename":"14400110.tif",
     "pagination":{
      "pgfolios":{
       "value":"54b"
      }
     }
    },
    {
     "filename":"14400111.tif",
     "pagination":{
      "pgfolios":{
       "value":"55a"
      }
     }
    },
    {
     "filename":"14400112.tif",
     "pagination":{
      "pgfolios":{
       "value":"55b"
      }
     }
    },
    {
     "filename":"14400113.tif",
     "pagination":{
      "pgfolios":{
       "value":"56a"
      }
     }
    },
    {
     "filename":"14400114.tif",
     "pagination":{
      "pgfolios":{
       "value":"56b"
      }
     }
    },
    {
     "filename":"14400115.tif",
     "pagination":{
      "pgfolios":{
       "value":"57a"
      }
     }
    },
    {
     "filename":"14400116.tif",
     "pagination":{
      "pgfolios":{
       "value":"57b"
      }
     }
    },
    {
     "filename":"14400117.tif",
     "pagination":{
      "pgfolios":{
       "value":"58a"
      }
     }
    },
    {
     "filename":"14400118.tif",
     "pagination":{
      "pgfolios":{
       "value":"58b"
      }
     }
    },
    {
     "filename":"14400119.tif",
     "pagination":{
      "pgfolios":{
       "value":"59a"
      }
     }
    },
    {
     "filename":"14400120.tif",
     "pagination":{
      "pgfolios":{
       "value":"59b"
      }
     }
    },
    {
     "filename":"14400121.tif",
     "pagination":{
      "pgfolios":{
       "value":"60a"
      }
     }
    },
    {
     "filename":"14400122.tif",
     "pagination":{
      "pgfolios":{
       "value":"60b"
      }
     }
    },
    {
     "filename":"14400123.tif",
     "pagination":{
      "pgfolios":{
       "value":"61a"
      }
     }
    },
    {
     "filename":"14400124.tif",
     "pagination":{
      "pgfolios":{
       "value":"61b"
      }
     }
    },
    {
     "filename":"14400125.tif",
     "pagination":{
      "pgfolios":{
       "value":"62a"
      }
     }
    },
    {
     "filename":"14400126.tif",
     "pagination":{
      "pgfolios":{
       "value":"62b"
      }
     }
    },
    {
     "filename":"14400127.tif",
     "pagination":{
      "pgfolios":{
       "value":"63a"
      }
     }
    },
    {
     "filename":"14400128.tif",
     "pagination":{
      "pgfolios":{
       "value":"63b"
      }
     }
    },
    {
     "filename":"14400129.tif",
     "pagination":{
      "pgfolios":{
       "value":"64a"
      }
     }
    },
    {
     "filename":"14400130.tif",
     "pagination":{
      "pgfolios":{
       "value":"64b"
      }
     }
    },
    {
     "filename":"14400131.tif",
     "pagination":{
      "pgfolios":{
       "value":"65a"
      }
     }
    },
    {
     "filename":"14400132.tif",
     "pagination":{
      "pgfolios":{
       "value":"65b"
      }
     }
    },
    {
     "filename":"14400133.tif",
     "pagination":{
      "pgfolios":{
       "value":"66a"
      }
     }
    },
    {
     "filename":"14400134.tif",
     "pagination":{
      "pgfolios":{
       "value":"66b"
      }
     }
    },
    {
     "filename":"14400135.tif",
     "pagination":{
      "pgfolios":{
       "value":"67a"
      }
     }
    },
    {
     "filename":"14400136.tif",
     "pagination":{
      "pgfolios":{
       "value":"67b"
      }
     }
    },
    {
     "filename":"14400137.tif",
     "pagination":{
      "pgfolios":{
       "value":"68a"
      }
     }
    },
    {
     "filename":"14400138.tif",
     "pagination":{
      "pgfolios":{
       "value":"68b"
      }
     }
    },
    {
     "filename":"14400139.tif",
     "pagination":{
      "pgfolios":{
       "value":"69a"
      }
     }
    },
    {
     "filename":"14400140.tif",
     "pagination":{
      "pgfolios":{
       "value":"69b"
      }
     }
    },
    {
     "filename":"14400141.tif",
     "pagination":{
      "pgfolios":{
       "value":"70a"
      }
     }
    },
    {
     "filename":"14400142.tif",
     "pagination":{
      "pgfolios":{
       "value":"70b"
      }
     }
    },
    {
     "filename":"14400143.tif",
     "pagination":{
      "pgfolios":{
       "value":"71a"
      }
     }
    },
    {
     "filename":"14400144.tif",
     "pagination":{
      "pgfolios":{
       "value":"71b"
      }
     }
    },
    {
     "filename":"14400145.tif",
     "pagination":{
      "pgfolios":{
       "value":"72a"
      }
     }
    },
    {
     "filename":"14400146.tif",
     "pagination":{
      "pgfolios":{
       "value":"72b"
      }
     }
    },
    {
     "filename":"14400147.tif",
     "pagination":{
      "pgfolios":{
       "value":"73a"
      }
     }
    },
    {
     "filename":"14400148.tif",
     "pagination":{
      "pgfolios":{
       "value":"73b"
      }
     }
    },
    {
     "filename":"14400149.tif",
     "pagination":{
      "pgfolios":{
       "value":"74a"
      }
     }
    },
    {
     "filename":"14400150.tif",
     "pagination":{
      "pgfolios":{
       "value":"74b"
      }
     }
    },
    {
     "filename":"14400151.tif",
     "pagination":{
      "pgfolios":{
       "value":"75a"
      }
     }
    },
    {
     "filename":"14400152.tif",
     "pagination":{
      "pgfolios":{
       "value":"75b"
      }
     }
    },
    {
     "filename":"14400153.tif",
     "pagination":{
      "pgfolios":{
       "value":"76a"
      }
     }
    },
    {
     "filename":"14400154.tif",
     "pagination":{
      "pgfolios":{
       "value":"76b"
      }
     }
    },
    {
     "filename":"14400155.tif",
     "pagination":{
      "pgfolios":{
       "value":"77a"
      }
     }
    },
    {
     "filename":"14400156.tif",
     "pagination":{
      "pgfolios":{
       "value":"77b"
      }
     }
    },
    {
     "filename":"14400157.tif",
     "pagination":{
      "pgfolios":{
       "value":"78a"
      }
     }
    },
    {
     "filename":"14400158.tif",
     "pagination":{
      "pgfolios":{
       "value":"78b"
      }
     }
    },
    {
     "filename":"14400159.tif",
     "pagination":{
      "pgfolios":{
       "value":"79a"
      }
     }
    },
    {
     "filename":"14400160.tif",
     "pagination":{
      "pgfolios":{
       "value":"79b"
      }
     }
    },
    {
     "filename":"14400161.tif",
     "pagination":{
      "pgfolios":{
       "value":"80a"
      }
     }
    },
    {
     "filename":"14400162.tif",
     "pagination":{
      "pgfolios":{
       "value":"80b"
      }
     }
    },
    {
     "filename":"14400163.tif",
     "pagination":{
      "pgfolios":{
       "value":"81a"
      }
     }
    },
    {
     "filename":"14400164.tif",
     "pagination":{
      "pgfolios":{
       "value":"81b"
      }
     }
    },
    {
     "filename":"14400165.tif",
     "pagination":{
      "pgfolios":{
       "value":"82a"
      }
     }
    },
    {
     "filename":"14400166.tif",
     "pagination":{
      "pgfolios":{
       "value":"82b"
      }
     }
    },
    {
     "filename":"14400167.tif",
     "pagination":{
      "pgfolios":{
       "value":"83a"
      }
     }
    },
    {
     "filename":"14400168.tif",
     "pagination":{
      "pgfolios":{
       "value":"83b"
      }
     }
    },
    {
     "filename":"14400169.tif",
     "pagination":{
      "pgfolios":{
       "value":"84a"
      }
     }
    },
    {
     "filename":"14400170.tif",
     "pagination":{
      "pgfolios":{
       "value":"84b"
      }
     }
    },
    {
     "filename":"14400171.tif",
     "pagination":{
      "pgfolios":{
       "value":"85a"
      }
     }
    },
    {
     "filename":"14400172.tif",
     "pagination":{
      "pgfolios":{
       "value":"85b"
      }
     }
    },
    {
     "filename":"14400173.tif",
     "pagination":{
      "pgfolios":{
       "value":"86a"
      }
     }
    },
    {
     "filename":"14400174.tif",
     "pagination":{
      "pgfolios":{
       "value":"86b"
      }
     }
    },
    {
     "filename":"14400175.tif",
     "pagination":{
      "pgfolios":{
       "value":"87a"
      }
     }
    },
    {
     "filename":"14400176.tif",
     "pagination":{
      "pgfolios":{
       "value":"87b"
      }
     }
    },
    {
     "filename":"14400177.tif",
     "pagination":{
      "pgfolios":{
       "value":"88a"
      }
     }
    },
    {
     "filename":"14400178.tif",
     "pagination":{
      "pgfolios":{
       "value":"88b"
      }
     }
    },
    {
     "filename":"14400179.tif",
     "pagination":{
      "pgfolios":{
       "value":"89a"
      }
     }
    },
    {
     "filename":"14400180.tif",
     "pagination":{
      "pgfolios":{
       "value":"89b"
      }
     }
    },
    {
     "filename":"14400181.tif",
     "pagination":{
      "pgfolios":{
       "value":"90a"
      }
     }
    },
    {
     "filename":"14400182.tif",
     "pagination":{
      "pgfolios":{
       "value":"90b"
      }
     }
    },
    {
     "filename":"14400183.tif",
     "pagination":{
      "pgfolios":{
       "value":"91a"
      }
     }
    },
    {
     "filename":"14400184.tif",
     "pagination":{
      "pgfolios":{
       "value":"91b"
      }
     }
    },
    {
     "filename":"14400185.tif",
     "pagination":{
      "pgfolios":{
       "value":"92a"
      }
     }
    },
    {
     "filename":"14400186.tif",
     "pagination":{
      "pgfolios":{
       "value":"92b"
      }
     }
    },
    {
     "filename":"14400187.tif",
     "pagination":{
      "pgfolios":{
       "value":"93a"
      }
     }
    },
    {
     "filename":"14400188.tif",
     "pagination":{
      "pgfolios":{
       "value":"93b"
      }
     }
    },
    {
     "filename":"14400189.tif",
     "pagination":{
      "pgfolios":{
       "value":"94a"
      }
     }
    },
    {
     "filename":"14400190.tif",
     "pagination":{
      "pgfolios":{
       "value":"94b"
      }
     }
    },
    {
     "filename":"14400191.tif",
     "pagination":{
      "pgfolios":{
       "value":"95a"
      }
     }
    },
    {
     "filename":"14400192.tif",
     "pagination":{
      "pgfolios":{
       "value":"95b"
      }
     }
    },
    {
     "filename":"14400193.tif",
     "pagination":{
      "pgfolios":{
       "value":"96a"
      }
     }
    },
    {
     "filename":"14400194.tif",
     "pagination":{
      "pgfolios":{
       "value":"96b"
      }
     }
    },
    {
     "filename":"14400195.tif",
     "pagination":{
      "pgfolios":{
       "value":"97a"
      }
     }
    },
    {
     "filename":"14400196.tif",
     "pagination":{
      "pgfolios":{
       "value":"97b"
      }
     }
    },
    {
     "filename":"14400197.tif",
     "pagination":{
      "pgfolios":{
       "value":"98a"
      }
     }
    },
    {
     "filename":"14400198.tif",
     "pagination":{
      "pgfolios":{
       "value":"98b"
      }
     }
    },
    {
     "filename":"14400199.tif",
     "pagination":{
      "pgfolios":{
       "value":"99a"
      }
     }
    },
    {
     "filename":"14400200.tif",
     "pagination":{
      "pgfolios":{
       "value":"99b"
      }
     }
    },
    {
     "filename":"14400201.tif",
     "pagination":{
      "pgfolios":{
       "value":"100a"
      }
     }
    },
    {
     "filename":"14400202.tif",
     "pagination":{
      "pgfolios":{
       "value":"100b"
      }
     }
    },
    {
     "filename":"14400203.tif",
     "pagination":{
      "pgfolios":{
       "value":"101a"
      }
     }
    },
    {
     "filename":"14400204.tif",
     "pagination":{
      "pgfolios":{
       "value":"101b"
      }
     }
    },
    {
     "filename":"14400205.tif",
     "pagination":{
      "pgfolios":{
       "value":"102a"
      }
     }
    },
    {
     "filename":"14400206.tif",
     "pagination":{
      "pgfolios":{
       "value":"102b"
      }
     }
    },
    {
     "filename":"14400207.tif",
     "pagination":{
      "pgfolios":{
       "value":"103a"
      }
     }
    },
    {
     "filename":"14400208.tif",
     "pagination":{
      "pgfolios":{
       "value":"103b"
      }
     }
    },
    {
     "filename":"14400209.tif",
     "pagination":{
      "pgfolios":{
       "value":"104a"
      }
     }
    },
    {
     "filename":"14400210.tif",
     "pagination":{
      "pgfolios":{
       "value":"104b"
      }
     }
    },
    {
     "filename":"14400211.tif",
     "pagination":{
      "pgfolios":{
       "value":"105a"
      }
     }
    },
    {
     "filename":"14400212.tif",
     "pagination":{
      "pgfolios":{
       "value":"105b"
      }
     }
    },
    {
     "filename":"14400213.tif",
     "pagination":{
      "pgfolios":{
       "value":"106a"
      }
     }
    },
    {
     "filename":"14400214.tif",
     "pagination":{
      "pgfolios":{
       "value":"106b"
      }
     }
    },
    {
     "filename":"14400215.tif",
     "pagination":{
      "pgfolios":{
       "value":"107a"
      }
     }
    },
    {
     "filename":"14400216.tif",
     "pagination":{
      "pgfolios":{
       "value":"107b"
      }
     }
    },
    {
     "filename":"14400217.tif",
     "pagination":{
      "pgfolios":{
       "value":"108a"
      }
     }
    },
    {
     "filename":"14400218.tif",
     "pagination":{
      "pgfolios":{
       "value":"108b"
      }
     }
    },
    {
     "filename":"14400219.tif",
     "pagination":{
      "pgfolios":{
       "value":"109a"
      }
     }
    },
    {
     "filename":"14400220.tif",
     "pagination":{
      "pgfolios":{
       "value":"109b"
      }
     }
    },
    {
     "filename":"14400221.tif",
     "pagination":{
      "pgfolios":{
       "value":"110a"
      }
     }
    },
    {
     "filename":"14400222.tif",
     "pagination":{
      "pgfolios":{
       "value":"110b"
      }
     }
    },
    {
     "filename":"14400223.tif",
     "pagination":{
      "pgfolios":{
       "value":"111a"
      }
     }
    },
    {
     "filename":"14400224.tif",
     "pagination":{
      "pgfolios":{
       "value":"111b"
      }
     }
    },
    {
     "filename":"14400225.tif",
     "pagination":{
      "pgfolios":{
       "value":"112a"
      }
     }
    },
    {
     "filename":"14400226.tif",
     "pagination":{
      "pgfolios":{
       "value":"112b"
      }
     }
    },
    {
     "filename":"14400227.tif",
     "pagination":{
      "pgfolios":{
       "value":"113a"
      }
     }
    },
    {
     "filename":"14400228.tif",
     "pagination":{
      "pgfolios":{
       "value":"113b"
      }
     }
    },
    {
     "filename":"14400229.tif",
     "pagination":{
      "pgfolios":{
       "value":"114a"
      }
     }
    },
    {
     "filename":"14400230.tif",
     "pagination":{
      "pgfolios":{
       "value":"114b"
      }
     }
    },
    {
     "filename":"14400231.tif",
     "pagination":{
      "pgfolios":{
       "value":"115a"
      }
     }
    },
    {
     "filename":"14400232.tif",
     "pagination":{
      "pgfolios":{
       "value":"115b"
      }
     }
    },
    {
     "filename":"14400233.tif",
     "pagination":{
      "pgfolios":{
       "value":"116a"
      }
     }
    },
    {
     "filename":"14400234.tif",
     "pagination":{
      "pgfolios":{
       "value":"116b"
      }
     }
    },
    {
     "filename":"14400235.tif",
     "pagination":{
      "pgfolios":{
       "value":"117a"
      }
     }
    },
    {
     "filename":"14400236.tif",
     "pagination":{
      "pgfolios":{
       "value":"117b"
      }
     }
    },
    {
     "filename":"14400237.tif",
     "pagination":{
      "pgfolios":{
       "value":"118a"
      }
     }
    },
    {
     "filename":"14400238.tif",
     "pagination":{
      "pgfolios":{
       "value":"118b"
      }
     }
    },
    {
     "filename":"14400239.tif",
     "pagination":{
      "pgfolios":{
       "value":"119a"
      }
     }
    },
    {
     "filename":"14400240.tif",
     "pagination":{
      "pgfolios":{
       "value":"119b"
      }
     }
    },
    {
     "filename":"14400241.tif",
     "pagination":{
      "pgfolios":{
       "value":"120a"
      }
     }
    },
    {
     "filename":"14400242.tif",
     "pagination":{
      "pgfolios":{
       "value":"120b"
      }
     }
    },
    {
     "filename":"14400243.tif",
     "pagination":{
      "pgfolios":{
       "value":"121a"
      }
     }
    },
    {
     "filename":"14400244.tif",
     "pagination":{
      "pgfolios":{
       "value":"121b"
      }
     }
    },
    {
     "filename":"14400245.tif",
     "pagination":{
      "pgfolios":{
       "value":"122a"
      }
     }
    },
    {
     "filename":"14400246.tif",
     "pagination":{
      "pgfolios":{
       "value":"122b"
      }
     }
    },
    {
     "filename":"14400247.tif",
     "pagination":{
      "pgfolios":{
       "value":"123a"
      }
     }
    },
    {
     "filename":"14400248.tif",
     "pagination":{
      "pgfolios":{
       "value":"123b"
      }
     }
    },
    {
     "filename":"14400249.tif",
     "pagination":{
      "pgfolios":{
       "value":"124a"
      }
     }
    },
    {
     "filename":"14400250.tif",
     "pagination":{
      "pgfolios":{
       "value":"124b"
      }
     }
    },
    {
     "filename":"14400251.tif",
     "pagination":{
      "pgfolios":{
       "value":"125a"
      }
     }
    },
    {
     "filename":"14400252.tif",
     "pagination":{
      "pgfolios":{
       "value":"125b"
      }
     }
    },
    {
     "filename":"14400253.tif",
     "pagination":{
      "pgfolios":{
       "value":"126a"
      }
     }
    },
    {
     "filename":"14400254.tif",
     "pagination":{
      "pgfolios":{
       "value":"126b"
      }
     }
    },
    {
     "filename":"14400255.tif",
     "pagination":{
      "pgfolios":{
       "value":"127a"
      }
     }
    },
    {
     "filename":"14400256.tif",
     "pagination":{
      "pgfolios":{
       "value":"127b"
      }
     }
    },
    {
     "filename":"14400257.tif",
     "pagination":{
      "pgfolios":{
       "value":"128a"
      }
     }
    },
    {
     "filename":"14400258.tif",
     "pagination":{
      "pgfolios":{
       "value":"128b"
      }
     }
    },
    {
     "filename":"14400259.tif",
     "pagination":{
      "pgfolios":{
       "value":"129a"
      }
     }
    },
    {
     "filename":"14400260.tif",
     "pagination":{
      "pgfolios":{
       "value":"129b"
      }
     }
    },
    {
     "filename":"14400261.tif",
     "pagination":{
      "pgfolios":{
       "value":"130a"
      }
     }
    },
    {
     "filename":"14400262.tif",
     "pagination":{
      "pgfolios":{
       "value":"130b"
      }
     }
    },
    {
     "filename":"14400263.tif",
     "pagination":{
      "pgfolios":{
       "value":"131a"
      }
     }
    },
    {
     "filename":"14400264.tif",
     "pagination":{
      "pgfolios":{
       "value":"131b"
      }
     }
    },
    {
     "filename":"14400265.tif",
     "pagination":{
      "pgfolios":{
       "value":"132a"
      }
     }
    },
    {
     "filename":"14400266.tif",
     "pagination":{
      "pgfolios":{
       "value":"132b"
      }
     }
    },
    {
     "filename":"14400267.tif",
     "pagination":{
      "pgfolios":{
       "value":"133a"
      }
     }
    },
    {
     "filename":"14400268.tif",
     "pagination":{
      "pgfolios":{
       "value":"133b"
      }
     }
    },
    {
     "filename":"14400269.tif",
     "pagination":{
      "pgfolios":{
       "value":"134a"
      }
     }
    },
    {
     "filename":"14400270.tif",
     "pagination":{
      "pgfolios":{
       "value":"134b"
      }
     }
    },
    {
     "filename":"14400271.tif",
     "pagination":{
      "pgfolios":{
       "value":"135a"
      }
     }
    },
    {
     "filename":"14400272.tif",
     "pagination":{
      "pgfolios":{
       "value":"135b"
      }
     }
    },
    {
     "filename":"14400273.tif",
     "pagination":{
      "pgfolios":{
       "value":"136a"
      }
     }
    },
    {
     "filename":"14400274.tif",
     "pagination":{
      "pgfolios":{
       "value":"136b"
      }
     }
    },
    {
     "filename":"14400275.tif",
     "pagination":{
      "pgfolios":{
       "value":"137a"
      }
     }
    },
    {
     "filename":"14400276.tif",
     "pagination":{
      "pgfolios":{
       "value":"137b"
      }
     }
    },
    {
     "filename":"14400277.tif",
     "pagination":{
      "pgfolios":{
       "value":"138a"
      }
     }
    },
    {
     "filename":"14400278.tif",
     "pagination":{
      "pgfolios":{
       "value":"138b"
      }
     }
    },
    {
     "filename":"14400279.tif",
     "pagination":{
      "pgfolios":{
       "value":"139a"
      }
     }
    },
    {
     "filename":"14400280.tif",
     "pagination":{
      "pgfolios":{
       "value":"139b"
      }
     }
    },
    {
     "filename":"14400281.tif",
     "pagination":{
      "pgfolios":{
       "value":"140a"
      }
     }
    },
    {
     "filename":"14400282.tif",
     "pagination":{
      "pgfolios":{
       "value":"140b"
      }
     }
    },
    {
     "filename":"14400283.tif",
     "pagination":{
      "pgfolios":{
       "value":"141a"
      }
     }
    },
    {
     "filename":"14400284.tif",
     "pagination":{
      "pgfolios":{
       "value":"141b"
      }
     }
    },
    {
     "filename":"14400285.tif",
     "pagination":{
      "pgfolios":{
       "value":"142a"
      }
     }
    },
    {
     "filename":"14400286.tif",
     "pagination":{
      "pgfolios":{
       "value":"142b"
      }
     }
    },
    {
     "filename":"14400287.tif",
     "pagination":{
      "pgfolios":{
       "value":"143a"
      }
     }
    },
    {
     "filename":"14400288.tif",
     "pagination":{
      "pgfolios":{
       "value":"143b"
      }
     }
    },
    {
     "filename":"14400289.tif",
     "pagination":{
      "pgfolios":{
       "value":"144a"
      }
     }
    },
    {
     "filename":"14400290.tif",
     "pagination":{
      "pgfolios":{
       "value":"144b"
      }
     }
    },
    {
     "filename":"14400291.tif",
     "pagination":{
      "pgfolios":{
       "value":"145a"
      }
     }
    },
    {
     "filename":"14400292.tif",
     "pagination":{
      "pgfolios":{
       "value":"145b"
      }
     }
    },
    {
     "filename":"14400293.tif",
     "pagination":{
      "pgfolios":{
       "value":"146a"
      }
     }
    },
    {
     "filename":"14400294.tif",
     "pagination":{
      "pgfolios":{
       "value":"146b"
      }
     }
    },
    {
     "filename":"14400295.tif",
     "pagination":{
      "pgfolios":{
       "value":"147a"
      }
     }
    },
    {
     "filename":"14400296.tif",
     "pagination":{
      "pgfolios":{
       "value":"147b"
      }
     }
    },
    {
     "filename":"14400297.tif",
     "pagination":{
      "pgfolios":{
       "value":"148a"
      }
     }
    },
    {
     "filename":"14400298.tif",
     "pagination":{
      "pgfolios":{
       "value":"148b"
      }
     }
    },
    {
     "filename":"14400299.tif",
     "pagination":{
      "pgfolios":{
       "value":"149a"
      }
     }
    },
    {
     "filename":"14400300.tif",
     "pagination":{
      "pgfolios":{
       "value":"149b"
      }
     }
    },
    {
     "filename":"14400301.tif",
     "pagination":{
      "pgfolios":{
       "value":"150a"
      }
     }
    },
    {
     "filename":"14400302.tif",
     "pagination":{
      "pgfolios":{
       "value":"150b"
      }
     }
    },
    {
     "filename":"14400303.tif",
     "pagination":{
      "pgfolios":{
       "value":"151a"
      }
     }
    },
    {
     "filename":"14400304.tif",
     "pagination":{
      "pgfolios":{
       "value":"151b"
      }
     }
    },
    {
     "filename":"14400305.tif",
     "pagination":{
      "pgfolios":{
       "value":"152a"
      }
     }
    },
    {
     "filename":"14400306.tif",
     "pagination":{
      "pgfolios":{
       "value":"152b"
      }
     }
    },
    {
     "filename":"14400307.tif",
     "pagination":{
      "pgfolios":{
       "value":"153a"
      }
     }
    },
    {
     "filename":"14400308.tif",
     "pagination":{
      "pgfolios":{
       "value":"153b"
      }
     }
    },
    {
     "filename":"14400309.tif",
     "pagination":{
      "pgfolios":{
       "value":"154a"
      }
     }
    },
    {
     "filename":"14400310.tif",
     "pagination":{
      "pgfolios":{
       "value":"154b"
      }
     }
    },
    {
     "filename":"14400311.tif",
     "pagination":{
      "pgfolios":{
       "value":"155a"
      }
     }
    },
    {
     "filename":"14400312.tif",
     "pagination":{
      "pgfolios":{
       "value":"155b"
      }
     }
    },
    {
     "filename":"14400313.tif",
     "pagination":{
      "pgfolios":{
       "value":"156a"
      }
     }
    },
    {
     "filename":"14400314.tif",
     "pagination":{
      "pgfolios":{
       "value":"156b"
      }
     }
    },
    {
     "filename":"14400315.tif",
     "pagination":{
      "pgfolios":{
       "value":"157a"
      }
     }
    },
    {
     "filename":"14400316.tif",
     "pagination":{
      "pgfolios":{
       "value":"157b"
      }
     }
    },
    {
     "filename":"14400317.tif",
     "pagination":{
      "pgfolios":{
       "value":"158a"
      }
     }
    },
    {
     "filename":"14400318.tif",
     "pagination":{
      "pgfolios":{
       "value":"158b"
      }
     }
    },
    {
     "filename":"14400319.tif",
     "pagination":{
      "pgfolios":{
       "value":"159a"
      }
     }
    },
    {
     "filename":"14400320.tif",
     "pagination":{
      "pgfolios":{
       "value":"159b"
      }
     }
    },
    {
     "filename":"14400321.tif",
     "pagination":{
      "pgfolios":{
       "value":"160a"
      }
     }
    },
    {
     "filename":"14400322.tif",
     "pagination":{
      "pgfolios":{
       "value":"160b"
      }
     }
    },
    {
     "filename":"14400323.tif",
     "pagination":{
      "pgfolios":{
       "value":"161a"
      }
     }
    },
    {
     "filename":"14400324.tif",
     "pagination":{
      "pgfolios":{
       "value":"161b"
      }
     }
    },
    {
     "filename":"14400325.tif",
     "pagination":{
      "pgfolios":{
       "value":"162a"
      }
     }
    },
    {
     "filename":"14400326.tif",
     "pagination":{
      "pgfolios":{
       "value":"162b"
      }
     }
    },
    {
     "filename":"14400327.tif",
     "pagination":{
      "pgfolios":{
       "value":"163a"
      }
     }
    },
    {
     "filename":"14400328.tif",
     "pagination":{
      "pgfolios":{
       "value":"163b"
      }
     }
    },
    {
     "filename":"14400329.tif",
     "pagination":{
      "pgfolios":{
       "value":"164a"
      }
     }
    },
    {
     "filename":"14400330.tif",
     "pagination":{
      "pgfolios":{
       "value":"164b"
      }
     }
    },
    {
     "filename":"14400331.tif",
     "pagination":{
      "pgfolios":{
       "value":"165a"
      }
     }
    },
    {
     "filename":"14400332.tif",
     "pagination":{
      "pgfolios":{
       "value":"165b"
      }
     }
    },
    {
     "filename":"14400333.tif",
     "pagination":{
      "pgfolios":{
       "value":"166a"
      }
     }
    },
    {
     "filename":"14400334.tif",
     "pagination":{
      "pgfolios":{
       "value":"166b"
      }
     }
    },
    {
     "filename":"14400335.tif",
     "pagination":{
      "pgfolios":{
       "value":"167a"
      }
     }
    },
    {
     "filename":"14400336.tif",
     "pagination":{
      "pgfolios":{
       "value":"167b"
      }
     }
    },
    {
     "filename":"14400337.tif",
     "pagination":{
      "pgfolios":{
       "value":"168a"
      }
     }
    },
    {
     "filename":"14400338.tif",
     "pagination":{
      "pgfolios":{
       "value":"168b"
      }
     }
    },
    {
     "filename":"14400339.tif",
     "pagination":{
      "pgfolios":{
       "value":"169a"
      }
     }
    },
    {
     "filename":"14400340.tif",
     "pagination":{
      "pgfolios":{
       "value":"169b"
      }
     }
    },
    {
     "filename":"14400341.tif",
     "pagination":{
      "pgfolios":{
       "value":"170a"
      }
     }
    },
    {
     "filename":"14400342.tif",
     "pagination":{
      "pgfolios":{
       "value":"170b"
      }
     }
    },
    {
     "filename":"14400343.tif",
     "pagination":{
      "pgfolios":{
       "value":"171a"
      }
     }
    },
    {
     "filename":"14400344.tif",
     "pagination":{
      "pgfolios":{
       "value":"171b"
      }
     }
    },
    {
     "filename":"14400345.tif",
     "pagination":{
      "pgfolios":{
       "value":"172a"
      }
     }
    },
    {
     "filename":"14400346.tif",
     "pagination":{
      "pgfolios":{
       "value":"172b"
      }
     }
    },
    {
     "filename":"14400347.tif",
     "pagination":{
      "pgfolios":{
       "value":"173a"
      }
     }
    },
    {
     "filename":"14400348.tif",
     "pagination":{
      "pgfolios":{
       "value":"173b"
      }
     }
    },
    {
     "filename":"14400349.tif",
     "pagination":{
      "pgfolios":{
       "value":"174a"
      }
     }
    },
    {
     "filename":"14400350.tif",
     "pagination":{
      "pgfolios":{
       "value":"174b"
      }
     }
    },
    {
     "filename":"14400351.tif",
     "pagination":{
      "pgfolios":{
       "value":"175a"
      }
     }
    },
    {
     "filename":"14400352.tif",
     "pagination":{
      "pgfolios":{
       "value":"175b"
      }
     }
    },
    {
     "filename":"14400353.tif",
     "pagination":{
      "pgfolios":{
       "value":"176a"
      }
     }
    },
    {
     "filename":"14400354.tif",
     "pagination":{
      "pgfolios":{
       "value":"176b"
      }
     }
    },
    {
     "filename":"14400355.tif",
     "pagination":{
      "pgfolios":{
       "value":"177a"
      }
     }
    },
    {
     "filename":"14400356.tif",
     "pagination":{
      "pgfolios":{
       "value":"177b"
      }
     }
    },
    {
     "filename":"14400357.tif",
     "pagination":{
      "pgfolios":{
       "value":"178a"
      }
     }
    },
    {
     "filename":"14400358.tif",
     "pagination":{
      "pgfolios":{
       "value":"178b"
      }
     }
    },
    {
     "filename":"14400359.tif",
     "pagination":{
      "pgfolios":{
       "value":"179a"
      }
     }
    },
    {
     "filename":"14400360.tif",
     "pagination":{
      "pgfolios":{
       "value":"179b"
      }
     }
    },
    {
     "filename":"14400361.tif",
     "pagination":{
      "pgfolios":{
       "value":"180a"
      }
     }
    },
    {
     "filename":"14400362.tif",
     "pagination":{
      "pgfolios":{
       "value":"180b"
      }
     }
    },
    {
     "filename":"14400363.tif",
     "pagination":{
      "pgfolios":{
       "value":"181a"
      }
     }
    },
    {
     "filename":"14400364.tif",
     "pagination":{
      "pgfolios":{
       "value":"181b"
      }
     }
    },
    {
     "filename":"14400365.tif",
     "pagination":{
      "pgfolios":{
       "value":"182a"
      }
     }
    },
    {
     "filename":"14400366.tif",
     "pagination":{
      "pgfolios":{
       "value":"182b"
      }
     }
    },
    {
     "filename":"14400367.tif",
     "pagination":{
      "pgfolios":{
       "value":"183a"
      }
     }
    },
    {
     "filename":"14400368.tif",
     "pagination":{
      "pgfolios":{
       "value":"183b"
      }
     }
    },
    {
     "filename":"14400369.tif",
     "pagination":{
      "pgfolios":{
       "value":"184a"
      }
     }
    },
    {
     "filename":"14400370.tif",
     "pagination":{
      "pgfolios":{
       "value":"184b"
      }
     }
    },
    {
     "filename":"14400371.tif",
     "pagination":{
      "pgfolios":{
       "value":"185a"
      }
     }
    },
    {
     "filename":"14400372.tif",
     "pagination":{
      "pgfolios":{
       "value":"185b"
      }
     }
    },
    {
     "filename":"14400373.tif",
     "pagination":{
      "pgfolios":{
       "value":"186a"
      }
     }
    },
    {
     "filename":"14400374.tif",
     "pagination":{
      "pgfolios":{
       "value":"186b"
      }
     }
    },
    {
     "filename":"14400375.tif",
     "pagination":{
      "pgfolios":{
       "value":"187a"
      }
     }
    },
    {
     "filename":"14400376.tif",
     "pagination":{
      "pgfolios":{
       "value":"187b"
      }
     }
    },
    {
     "filename":"14400377.tif",
     "pagination":{
      "pgfolios":{
       "value":"188a"
      }
     }
    },
    {
     "filename":"14400378.tif",
     "pagination":{
      "pgfolios":{
       "value":"188b"
      }
     }
    },
    {
     "filename":"14400379.tif",
     "pagination":{
      "pgfolios":{
       "value":"189a"
      }
     }
    },
    {
     "filename":"14400380.tif",
     "pagination":{
      "pgfolios":{
       "value":"189b"
      }
     }
    },
    {
     "filename":"14400381.tif",
     "pagination":{
      "pgfolios":{
       "value":"190a"
      }
     }
    },
    {
     "filename":"14400382.tif",
     "pagination":{
      "pgfolios":{
       "value":"190b"
      }
     }
    },
    {
     "filename":"14400383.tif",
     "pagination":{
      "pgfolios":{
       "value":"191a"
      }
     }
    },
    {
     "filename":"14400384.tif",
     "pagination":{
      "pgfolios":{
       "value":"191b"
      }
     }
    },
    {
     "filename":"14400385.tif",
     "pagination":{
      "pgfolios":{
       "value":"192a"
      }
     }
    },
    {
     "filename":"14400386.tif",
     "pagination":{
      "pgfolios":{
       "value":"192b"
      }
     }
    },
    {
     "filename":"14400387.tif",
     "pagination":{
      "pgfolios":{
       "value":"193a"
      }
     }
    },
    {
     "filename":"14400388.tif",
     "pagination":{
      "pgfolios":{
       "value":"193b"
      }
     }
    },
    {
     "filename":"14400389.tif",
     "pagination":{
      "pgfolios":{
       "value":"194a"
      }
     }
    },
    {
     "filename":"14400390.tif",
     "pagination":{
      "pgfolios":{
       "value":"194b"
      }
     }
    },
    {
     "filename":"14400391.tif",
     "pagination":{
      "pgfolios":{
       "value":"195a"
      }
     }
    },
    {
     "filename":"14400392.tif",
     "pagination":{
      "pgfolios":{
       "value":"195b"
      }
     }
    },
    {
     "filename":"14400393.tif",
     "pagination":{
      "pgfolios":{
       "value":"196a"
      }
     }
    },
    {
     "filename":"14400394.tif",
     "pagination":{
      "pgfolios":{
       "value":"196b"
      }
     }
    },
    {
     "filename":"14400395.tif",
     "pagination":{
      "pgfolios":{
       "value":"197a"
      }
     }
    },
    {
     "filename":"14400396.tif",
     "pagination":{
      "pgfolios":{
       "value":"197b"
      }
     }
    },
    {
     "filename":"14400397.tif",
     "pagination":{
      "pgfolios":{
       "value":"198a"
      }
     }
    },
    {
     "filename":"14400398.tif",
     "pagination":{
      "pgfolios":{
       "value":"198b"
      }
     }
    },
    {
     "filename":"14400399.tif",
     "pagination":{
      "pgfolios":{
       "value":"199a"
      }
     }
    },
    {
     "filename":"14400400.tif",
     "pagination":{
      "pgfolios":{
       "value":"199b"
      }
     }
    },
    {
     "filename":"14400401.tif",
     "pagination":{
      "pgfolios":{
       "value":"200a"
      }
     }
    },
    {
     "filename":"14400402.tif",
     "pagination":{
      "pgfolios":{
       "value":"200b"
      }
     }
    },
    {
     "filename":"14400403.tif",
     "pagination":{
      "pgfolios":{
       "value":"201a"
      }
     }
    },
    {
     "filename":"14400404.tif",
     "pagination":{
      "pgfolios":{
       "value":"201b"
      }
     }
    },
    {
     "filename":"14400405.tif",
     "pagination":{
      "pgfolios":{
       "value":"202a"
      }
     }
    },
    {
     "filename":"14400406.tif",
     "pagination":{
      "pgfolios":{
       "value":"202b"
      }
     }
    },
    {
     "filename":"14400407.tif",
     "pagination":{
      "pgfolios":{
       "value":"203a"
      }
     }
    },
    {
     "filename":"14400408.tif",
     "pagination":{
      "pgfolios":{
       "value":"203b"
      }
     }
    },
    {
     "filename":"14400409.tif",
     "pagination":{
      "pgfolios":{
       "value":"204a"
      }
     }
    },
    {
     "filename":"14400410.tif",
     "pagination":{
      "pgfolios":{
       "value":"204b"
      }
     }
    },
    {
     "filename":"14400411.tif",
     "pagination":{
      "pgfolios":{
       "value":"205a"
      }
     }
    },
    {
     "filename":"14400412.tif",
     "pagination":{
      "pgfolios":{
       "value":"205b"
      }
     }
    },
    {
     "filename":"14400413.tif",
     "pagination":{
      "pgfolios":{
       "value":"206a"
      }
     }
    },
    {
     "filename":"14400414.tif",
     "pagination":{
      "pgfolios":{
       "value":"206b"
      }
     }
    },
    {
     "filename":"14400415.tif",
     "pagination":{
      "pgfolios":{
       "value":"207a"
      }
     }
    },
    {
     "filename":"14400416.tif",
     "pagination":{
      "pgfolios":{
       "value":"207b"
      }
     }
    },
    {
     "filename":"14400417.tif",
     "pagination":{
      "pgfolios":{
       "value":"208a"
      }
     }
    },
    {
     "filename":"14400418.tif",
     "pagination":{
      "pgfolios":{
       "value":"208b"
      }
     }
    },
    {
     "filename":"14400419.tif",
     "pagination":{
      "pgfolios":{
       "value":"209a"
      }
     }
    },
    {
     "filename":"14400420.tif",
     "pagination":{
      "pgfolios":{
       "value":"209b"
      }
     }
    },
    {
     "filename":"14400421.tif",
     "pagination":{
      "pgfolios":{
       "value":"210a"
      }
     }
    },
    {
     "filename":"14400422.tif",
     "pagination":{
      "pgfolios":{
       "value":"210b"
      }
     }
    },
    {
     "filename":"14400423.tif",
     "pagination":{
      "pgfolios":{
       "value":"211a"
      }
     }
    },
    {
     "filename":"14400424.tif",
     "pagination":{
      "pgfolios":{
       "value":"211b"
      }
     }
    },
    {
     "filename":"14400425.tif",
     "pagination":{
      "pgfolios":{
       "value":"212a"
      }
     }
    },
    {
     "filename":"14400426.tif",
     "pagination":{
      "pgfolios":{
       "value":"212b"
      }
     }
    },
    {
     "filename":"14400427.tif",
     "pagination":{
      "pgfolios":{
       "value":"213a"
      }
     }
    },
    {
     "filename":"14400428.tif",
     "pagination":{
      "pgfolios":{
       "value":"213b"
      }
     }
    },
    {
     "filename":"14400429.tif",
     "pagination":{
      "pgfolios":{
       "value":"214a"
      }
     }
    },
    {
     "filename":"14400430.tif",
     "pagination":{
      "pgfolios":{
       "value":"214b"
      }
     }
    },
    {
     "filename":"14400431.tif",
     "pagination":{
      "pgfolios":{
       "value":"215a"
      }
     }
    },
    {
     "filename":"14400432.tif",
     "pagination":{
      "pgfolios":{
       "value":"215b"
      }
     }
    },
    {
     "filename":"14400433.tif",
     "pagination":{
      "pgfolios":{
       "value":"216a"
      }
     }
    },
    {
     "filename":"14400434.tif",
     "pagination":{
      "pgfolios":{
       "value":"216b"
      }
     }
    },
    {
     "filename":"14400435.tif",
     "pagination":{
      "pgfolios":{
       "value":"217a"
      }
     }
    },
    {
     "filename":"14400436.tif",
     "pagination":{
      "pgfolios":{
       "value":"217b"
      }
     }
    },
    {
     "filename":"14400437.tif",
     "pagination":{
      "pgfolios":{
       "value":"218a"
      }
     }
    },
    {
     "filename":"14400438.tif",
     "pagination":{
      "pgfolios":{
       "value":"218b"
      }
     }
    },
    {
     "filename":"14400439.tif",
     "pagination":{
      "pgfolios":{
       "value":"219a"
      }
     }
    },
    {
     "filename":"14400440.tif",
     "pagination":{
      "pgfolios":{
       "value":"219b"
      }
     }
    },
    {
     "filename":"14400441.tif",
     "pagination":{
      "pgfolios":{
       "value":"220a"
      }
     }
    },
    {
     "filename":"14400442.tif",
     "pagination":{
      "pgfolios":{
       "value":"220b"
      }
     }
    },
    {
     "filename":"14400443.tif",
     "pagination":{
      "pgfolios":{
       "value":"221a"
      }
     }
    },
    {
     "filename":"14400444.tif",
     "pagination":{
      "pgfolios":{
       "value":"221b"
      }
     }
    },
    {
     "filename":"14400445.tif",
     "pagination":{
      "pgfolios":{
       "value":"222a"
      }
     }
    },
    {
     "filename":"14400446.tif",
     "pagination":{
      "pgfolios":{
       "value":"222b"
      }
     }
    },
    {
     "filename":"14400447.tif",
     "pagination":{
      "pgfolios":{
       "value":"223a"
      }
     }
    },
    {
     "filename":"14400448.tif",
     "pagination":{
      "pgfolios":{
       "value":"223b"
      }
     }
    },
    {
     "filename":"14400449.tif",
     "pagination":{
      "pgfolios":{
       "value":"224a"
      }
     }
    },
    {
     "filename":"14400450.tif",
     "pagination":{
      "pgfolios":{
       "value":"224b"
      }
     }
    },
    {
     "filename":"14400451.tif",
     "pagination":{
      "pgfolios":{
       "value":"225a"
      }
     }
    },
    {
     "filename":"14400452.tif",
     "pagination":{
      "pgfolios":{
       "value":"225b"
      }
     }
    },
    {
     "filename":"14400453.tif",
     "pagination":{
      "pgfolios":{
       "value":"226a"
      }
     }
    },
    {
     "filename":"14400454.tif",
     "pagination":{
      "pgfolios":{
       "value":"226b"
      }
     }
    },
    {
     "filename":"14400455.tif",
     "pagination":{
      "pgfolios":{
       "value":"227a"
      }
     }
    },
    {
     "filename":"14400456.tif",
     "pagination":{
      "pgfolios":{
       "value":"227b"
      }
     }
    },
    {
     "filename":"14400457.tif",
     "pagination":{
      "pgfolios":{
       "value":"228a"
      }
     }
    },
    {
     "filename":"14400458.tif",
     "pagination":{
      "pgfolios":{
       "value":"228b"
      }
     }
    },
    {
     "filename":"14400459.tif",
     "pagination":{
      "pgfolios":{
       "value":"229a"
      }
     }
    },
    {
     "filename":"14400460.tif",
     "pagination":{
      "pgfolios":{
       "value":"229b"
      }
     }
    },
    {
     "filename":"14400461.tif",
     "pagination":{
      "pgfolios":{
       "value":"230a"
      }
     }
    },
    {
     "filename":"14400462.tif",
     "pagination":{
      "pgfolios":{
       "value":"230b"
      }
     }
    },
    {
     "filename":"14400463.tif",
     "pagination":{
      "pgfolios":{
       "value":"231a"
      }
     }
    },
    {
     "filename":"14400464.tif",
     "pagination":{
      "pgfolios":{
       "value":"231b"
      }
     }
    },
    {
     "filename":"14400465.tif",
     "pagination":{
      "pgfolios":{
       "value":"232a"
      }
     }
    },
    {
     "filename":"14400466.tif",
     "pagination":{
      "pgfolios":{
       "value":"232b"
      }
     }
    },
    {
     "filename":"14400467.tif",
     "pagination":{
      "pgfolios":{
       "value":"233a"
      }
     }
    },
    {
     "filename":"14400468.tif",
     "pagination":{
      "pgfolios":{
       "value":"233b"
      }
     }
    },
    {
     "filename":"14400469.tif",
     "pagination":{
      "pgfolios":{
       "value":"234a"
      }
     }
    },
    {
     "filename":"14400470.tif",
     "pagination":{
      "pgfolios":{
       "value":"234b"
      }
     }
    },
    {
     "filename":"14400471.tif",
     "pagination":{
      "pgfolios":{
       "value":"235a"
      }
     }
    },
    {
     "filename":"14400472.tif",
     "pagination":{
      "pgfolios":{
       "value":"235b"
      }
     }
    },
    {
     "filename":"14400473.tif",
     "pagination":{
      "pgfolios":{
       "value":"236a"
      }
     }
    },
    {
     "filename":"14400474.tif",
     "pagination":{
      "pgfolios":{
       "value":"236b"
      }
     }
    },
    {
     "filename":"14400475.tif",
     "pagination":{
      "pgfolios":{
       "value":"237a"
      }
     }
    },
    {
     "filename":"14400476.tif",
     "pagination":{
      "pgfolios":{
       "value":"237b"
      }
     }
    },
    {
     "filename":"14400477.tif",
     "pagination":{
      "pgfolios":{
       "value":"238a"
      }
     }
    },
    {
     "filename":"14400478.tif",
     "pagination":{
      "pgfolios":{
       "value":"238b"
      }
     }
    },
    {
     "filename":"14400479.tif",
     "pagination":{
      "pgfolios":{
       "value":"239a"
      }
     }
    },
    {
     "filename":"14400480.tif",
     "pagination":{
      "pgfolios":{
       "value":"239b"
      }
     }
    },
    {
     "filename":"14400481.tif",
     "pagination":{
      "pgfolios":{
       "value":"240a"
      }
     }
    },
    {
     "filename":"14400482.tif",
     "pagination":{
      "pgfolios":{
       "value":"240b"
      }
     }
    },
    {
     "filename":"14400483.tif",
     "pagination":{
      "pgfolios":{
       "value":"241a"
      }
     }
    },
    {
     "filename":"14400484.tif",
     "pagination":{
      "pgfolios":{
       "value":"241b"
      }
     }
    },
    {
     "filename":"14400485.tif",
     "pagination":{
      "pgfolios":{
       "value":"242a"
      }
     }
    },
    {
     "filename":"14400486.tif",
     "pagination":{
      "pgfolios":{
       "value":"242b"
      }
     }
    },
    {
     "filename":"14400487.tif",
     "pagination":{
      "pgfolios":{
       "value":"243a"
      }
     }
    },
    {
     "filename":"14400488.tif",
     "pagination":{
      "pgfolios":{
       "value":"243b"
      }
     }
    },
    {
     "filename":"14400489.tif",
     "pagination":{
      "pgfolios":{
       "value":"244a"
      }
     }
    },
    {
     "filename":"14400490.tif",
     "pagination":{
      "pgfolios":{
       "value":"244b"
      }
     }
    },
    {
     "filename":"14400491.tif",
     "pagination":{
      "pgfolios":{
       "value":"245a"
      }
     }
    },
    {
     "filename":"14400492.tif",
     "pagination":{
      "pgfolios":{
       "value":"245b"
      }
     }
    },
    {
     "filename":"14400493.tif",
     "pagination":{
      "pgfolios":{
       "value":"246a"
      }
     }
    },
    {
     "filename":"14400494.tif",
     "pagination":{
      "pgfolios":{
       "value":"246b"
      }
     }
    },
    {
     "filename":"14400495.tif",
     "pagination":{
      "pgfolios":{
       "value":"247a"
      }
     }
    },
    {
     "filename":"14400496.tif",
     "pagination":{
      "pgfolios":{
       "value":"247b"
      }
     }
    },
    {
     "filename":"14400497.tif",
     "pagination":{
      "pgfolios":{
       "value":"248a"
      }
     }
    },
    {
     "filename":"14400498.tif",
     "pagination":{
      "pgfolios":{
       "value":"248b"
      }
     }
    },
    {
     "filename":"14400499.tif",
     "pagination":{
      "pgfolios":{
       "value":"249a"
      }
     }
    },
    {
     "filename":"14400500.tif",
     "pagination":{
      "pgfolios":{
       "value":"249b"
      }
     }
    },
    {
     "filename":"14400501.tif",
     "pagination":{
      "pgfolios":{
       "value":"250a"
      }
     }
    },
    {
     "filename":"14400502.tif",
     "pagination":{
      "pgfolios":{
       "value":"250b"
      }
     }
    },
    {
     "filename":"14400503.tif",
     "pagination":{
      "pgfolios":{
       "value":"251a"
      }
     }
    },
    {
     "filename":"14400504.tif",
     "pagination":{
      "pgfolios":{
       "value":"251b"
      }
     }
    },
    {
     "filename":"14400505.tif",
     "pagination":{
      "pgfolios":{
       "value":"252a"
      }
     }
    },
    {
     "filename":"14400506.tif",
     "pagination":{
      "pgfolios":{
       "value":"252b"
      }
     }
    },
    {
     "filename":"14400507.tif",
     "pagination":{
      "pgfolios":{
       "value":"253a"
      }
     }
    },
    {
     "filename":"14400508.tif",
     "pagination":{
      "pgfolios":{
       "value":"253b"
      }
     }
    },
    {
     "filename":"14400509.tif",
     "pagination":{
      "pgfolios":{
       "value":"254a"
      }
     }
    },
    {
     "filename":"14400510.tif",
     "pagination":{
      "pgfolios":{
       "value":"254b"
      }
     }
    },
    {
     "filename":"14400511.tif",
     "pagination":{
      "pgfolios":{
       "value":"255a"
      }
     }
    },
    {
     "filename":"14400512.tif",
     "pagination":{
      "pgfolios":{
       "value":"255b"
      }
     }
    },
    {
     "filename":"14400513.tif",
     "pagination":{
      "pgfolios":{
       "value":"256a"
      }
     }
    },
    {
     "filename":"14400514.tif",
     "pagination":{
      "pgfolios":{
       "value":"256b"
      }
     }
    },
    {
     "filename":"14400515.tif",
     "pagination":{
      "pgfolios":{
       "value":"257a"
      }
     }
    },
    {
     "filename":"14400516.tif",
     "pagination":{
      "pgfolios":{
       "value":"257b"
      }
     }
    },
    {
     "filename":"14400517.tif",
     "pagination":{
      "pgfolios":{
       "value":"258a"
      }
     }
    },
    {
     "filename":"14400518.tif",
     "pagination":{
      "pgfolios":{
       "value":"258b"
      }
     }
    },
    {
     "filename":"14400519.tif",
     "pagination":{
      "pgfolios":{
       "value":"259a"
      }
     }
    },
    {
     "filename":"14400520.tif",
     "pagination":{
      "pgfolios":{
       "value":"259b"
      }
     }
    },
    {
     "filename":"14400521.tif",
     "pagination":{
      "pgfolios":{
       "value":"260a"
      }
     }
    },
    {
     "filename":"14400522.tif",
     "pagination":{
      "pgfolios":{
       "value":"260b"
      }
     }
    },
    {
     "filename":"14400523.tif",
     "pagination":{
      "pgfolios":{
       "value":"261a"
      }
     }
    },
    {
     "filename":"14400524.tif",
     "pagination":{
      "pgfolios":{
       "value":"261b"
      }
     }
    },
    {
     "filename":"14400525.tif",
     "pagination":{
      "pgfolios":{
       "value":"262a"
      }
     }
    },
    {
     "filename":"14400526.tif",
     "pagination":{
      "pgfolios":{
       "value":"262b"
      }
     }
    },
    {
     "filename":"14400527.tif",
     "pagination":{
      "pgfolios":{
       "value":"263a"
      }
     }
    },
    {
     "filename":"14400528.tif",
     "pagination":{
      "pgfolios":{
       "value":"263b"
      }
     }
    },
    {
     "filename":"14400529.tif",
     "pagination":{
      "pgfolios":{
       "value":"264a"
      }
     }
    },
    {
     "filename":"14400530.tif",
     "pagination":{
      "pgfolios":{
       "value":"264b"
      }
     }
    },
    {
     "filename":"14400531.tif",
     "pagination":{
      "pgfolios":{
       "value":"265a"
      }
     }
    },
    {
     "filename":"14400532.tif",
     "pagination":{
      "pgfolios":{
       "value":"265b"
      }
     }
    },
    {
     "filename":"14400533.tif",
     "pagination":{
      "pgfolios":{
       "value":"266a"
      }
     }
    },
    {
     "filename":"14400534.tif",
     "pagination":{
      "pgfolios":{
       "value":"266b"
      }
     }
    },
    {
     "filename":"14400535.tif",
     "pagination":{
      "pgfolios":{
       "value":"267a"
      }
     }
    },
    {
     "filename":"14400536.tif",
     "pagination":{
      "pgfolios":{
       "value":"267b"
      }
     }
    },
    {
     "filename":"14400537.tif",
     "pagination":{
      "pgfolios":{
       "value":"268a"
      }
     }
    },
    {
     "filename":"14400538.tif",
     "pagination":{
      "pgfolios":{
       "value":"268b"
      }
     }
    },
    {
     "filename":"14400539.tif",
     "pagination":{
      "pgfolios":{
       "value":"269a"
      }
     }
    },
    {
     "filename":"14400540.tif",
     "pagination":{
      "pgfolios":{
       "value":"269b"
      }
     }
    },
    {
     "filename":"14400541.tif",
     "pagination":{
      "pgfolios":{
       "value":"270a"
      }
     }
    },
    {
     "filename":"14400542.tif",
     "pagination":{
      "pgfolios":{
       "value":"270b"
      }
     }
    },
    {
     "filename":"14400543.tif",
     "pagination":{
      "pgfolios":{
       "value":"271a"
      }
     }
    },
    {
     "filename":"14400544.tif",
     "pagination":{
      "pgfolios":{
       "value":"271b"
      }
     }
    },
    {
     "filename":"14400545.tif",
     "pagination":{
      "pgfolios":{
       "value":"272a"
      }
     }
    },
    {
     "filename":"14400546.tif",
     "pagination":{
      "pgfolios":{
       "value":"272b"
      }
     }
    },
    {
     "filename":"14400547.tif",
     "pagination":{
      "pgfolios":{
       "value":"273a"
      }
     }
    },
    {
     "filename":"14400548.tif",
     "pagination":{
      "pgfolios":{
       "value":"273b"
      }
     }
    },
    {
     "filename":"14400549.tif",
     "pagination":{
      "pgfolios":{
       "value":"274a"
      }
     }
    },
    {
     "filename":"14400550.tif",
     "pagination":{
      "pgfolios":{
       "value":"274b"
      }
     }
    },
    {
     "filename":"14400551.tif",
     "pagination":{
      "pgfolios":{
       "value":"275a"
      }
     }
    },
    {
     "filename":"14400552.tif",
     "pagination":{
      "pgfolios":{
       "value":"275b"
      }
     }
    },
    {
     "filename":"14400553.tif",
     "pagination":{
      "pgfolios":{
       "value":"276a"
      }
     }
    },
    {
     "filename":"14400554.tif",
     "pagination":{
      "pgfolios":{
       "value":"276b"
      }
     }
    },
    {
     "filename":"14400555.tif",
     "pagination":{
      "pgfolios":{
       "value":"277a"
      }
     }
    },
    {
     "filename":"14400556.tif",
     "pagination":{
      "pgfolios":{
       "value":"277b"
      }
     }
    },
    {
     "filename":"14400557.tif",
     "pagination":{
      "pgfolios":{
       "value":"278a"
      }
     }
    },
    {
     "filename":"14400558.tif",
     "pagination":{
      "pgfolios":{
       "value":"278b"
      }
     }
    },
    {
     "filename":"14400559.tif",
     "pagination":{
      "pgfolios":{
       "value":"279a"
      }
     }
    },
    {
     "filename":"14400560.tif",
     "pagination":{
      "pgfolios":{
       "value":"279b"
      }
     }
    },
    {
     "filename":"14400561.tif",
     "pagination":{
      "pgfolios":{
       "value":"280a"
      }
     }
    },
    {
     "filename":"14400562.tif",
     "pagination":{
      "pgfolios":{
       "value":"280b"
      }
     }
    },
    {
     "filename":"14400563.tif",
     "pagination":{
      "pgfolios":{
       "value":"281a"
      }
     }
    },
    {
     "filename":"14400564.tif",
     "pagination":{
      "pgfolios":{
       "value":"281b"
      }
     }
    },
    {
     "filename":"14400565.tif",
     "pagination":{
      "pgfolios":{
       "value":"282a"
      }
     }
    },
    {
     "filename":"14400566.tif",
     "pagination":{
      "pgfolios":{
       "value":"282b"
      }
     }
    },
    {
     "filename":"14400567.tif",
     "pagination":{
      "pgfolios":{
       "value":"283a"
      }
     }
    },
    {
     "filename":"14400568.tif",
     "pagination":{
      "pgfolios":{
       "value":"283b"
      }
     }
    },
    {
     "filename":"14400569.tif",
     "pagination":{
      "pgfolios":{
       "value":"284a"
      }
     }
    },
    {
     "filename":"14400570.tif",
     "pagination":{
      "pgfolios":{
       "value":"284b"
      }
     }
    },
    {
     "filename":"14400571.tif",
     "pagination":{
      "pgfolios":{
       "value":"285a"
      }
     }
    },
    {
     "filename":"14400572.tif",
     "pagination":{
      "pgfolios":{
       "value":"285b"
      }
     }
    },
    {
     "filename":"14400573.tif",
     "pagination":{
      "pgfolios":{
       "value":"286a"
      }
     }
    },
    {
     "filename":"14400574.tif",
     "pagination":{
      "pgfolios":{
       "value":"286b"
      }
     }
    },
    {
     "filename":"14400575.tif",
     "pagination":{
      "pgfolios":{
       "value":"287a"
      }
     }
    },
    {
     "filename":"14400576.tif",
     "pagination":{
      "pgfolios":{
       "value":"287b"
      }
     }
    },
    {
     "filename":"14400577.tif",
     "pagination":{
      "pgfolios":{
       "value":"288a"
      }
     }
    },
    {
     "filename":"14400578.tif",
     "pagination":{
      "pgfolios":{
       "value":"288b"
      }
     }
    },
    {
     "filename":"14400579.tif",
     "pagination":{
      "pgfolios":{
       "value":"289a"
      }
     }
    },
    {
     "filename":"14400580.tif",
     "pagination":{
      "pgfolios":{
       "value":"289b"
      }
     }
    },
    {
     "filename":"14400581.tif",
     "pagination":{
      "pgfolios":{
       "value":"290a"
      }
     }
    },
    {
     "filename":"14400582.tif",
     "pagination":{
      "pgfolios":{
       "value":"290b"
      }
     }
    },
    {
     "filename":"14400583.tif",
     "pagination":{
      "pgfolios":{
       "value":"291a"
      }
     }
    },
    {
     "filename":"14400584.tif",
     "pagination":{
      "pgfolios":{
       "value":"291b"
      }
     }
    },
    {
     "filename":"14400585.tif",
     "pagination":{
      "pgfolios":{
       "value":"292a"
      }
     }
    },
    {
     "filename":"14400586.tif",
     "pagination":{
      "pgfolios":{
       "value":"292b"
      }
     }
    },
    {
     "filename":"14400587.tif",
     "pagination":{
      "pgfolios":{
       "value":"293a"
      }
     }
    },
    {
     "filename":"14400588.tif",
     "pagination":{
      "pgfolios":{
       "value":"293b"
      }
     }
    },
    {
     "filename":"14400589.tif",
     "pagination":{
      "pgfolios":{
       "value":"294a"
      }
     }
    },
    {
     "filename":"14400590.tif",
     "pagination":{
      "pgfolios":{
       "value":"294b"
      }
     }
    },
    {
     "filename":"14400591.tif",
     "pagination":{
      "pgfolios":{
       "value":"295a"
      }
     }
    },
    {
     "filename":"14400592.tif",
     "pagination":{
      "pgfolios":{
       "value":"295b"
      }
     }
    },
    {
     "filename":"14400593.tif",
     "pagination":{
      "pgfolios":{
       "value":"296a"
      }
     }
    },
    {
     "filename":"14400594.tif",
     "pagination":{
      "pgfolios":{
       "value":"296b"
      }
     }
    },
    {
     "filename":"14400595.tif",
     "pagination":{
      "pgfolios":{
       "value":"297a"
      }
     }
    },
    {
     "filename":"14400596.tif",
     "pagination":{
      "pgfolios":{
       "value":"297b"
      }
     }
    },
    {
     "filename":"14400597.tif",
     "pagination":{
      "pgfolios":{
       "value":"298a"
      }
     }
    },
    {
     "filename":"14400598.tif",
     "pagination":{
      "pgfolios":{
       "value":"298b"
      }
     }
    },
    {
     "filename":"14400599.tif",
     "pagination":{
      "pgfolios":{
       "value":"299a"
      }
     }
    },
    {
     "filename":"14400600.tif",
     "pagination":{
      "pgfolios":{
       "value":"299b"
      }
     }
    },
    {
     "filename":"14400601.tif",
     "pagination":{
      "pgfolios":{
       "value":"300a"
      }
     }
    },
    {
     "filename":"14400602.tif",
     "pagination":{
      "pgfolios":{
       "value":"300b"
      }
     }
    },
    {
     "filename":"14400603.tif",
     "pagination":{
      "pgfolios":{
       "value":"301a"
      }
     }
    },
    {
     "filename":"14400604.tif",
     "pagination":{
      "pgfolios":{
       "value":"301b"
      }
     }
    },
    {
     "filename":"14400605.tif",
     "pagination":{
      "pgfolios":{
       "value":"302a"
      }
     }
    },
    {
     "filename":"14400606.tif",
     "pagination":{
      "pgfolios":{
       "value":"302b"
      }
     }
    },
    {
     "filename":"14400607.tif",
     "pagination":{
      "pgfolios":{
       "value":"303a"
      }
     }
    },
    {
     "filename":"14400608.tif",
     "pagination":{
      "pgfolios":{
       "value":"303b"
      }
     }
    },
    {
     "filename":"14400609.tif",
     "pagination":{
      "pgfolios":{
       "value":"304a"
      }
     }
    },
    {
     "filename":"14400610.tif",
     "pagination":{
      "pgfolios":{
       "value":"304b"
      }
     }
    },
    {
     "filename":"14400611.tif",
     "pagination":{
      "pgfolios":{
       "value":"305a"
      }
     }
    },
    {
     "filename":"14400612.tif",
     "pagination":{
      "pgfolios":{
       "value":"305b"
      }
     }
    },
    {
     "filename":"14400613.tif",
     "pagination":{
      "pgfolios":{
       "value":"306a"
      }
     }
    },
    {
     "filename":"14400614.tif",
     "pagination":{
      "pgfolios":{
       "value":"306b"
      }
     }
    },
    {
     "filename":"14400615.tif",
     "pagination":{
      "pgfolios":{
       "value":"307a"
      }
     }
    },
    {
     "filename":"14400616.tif",
     "pagination":{
      "pgfolios":{
       "value":"307b"
      }
     }
    },
    {
     "filename":"14400617.tif",
     "pagination":{
      "pgfolios":{
       "value":"308a"
      }
     }
    },
    {
     "filename":"14400618.tif",
     "pagination":{
      "pgfolios":{
       "value":"308b"
      }
     }
    },
    {
     "filename":"14400619.tif",
     "pagination":{
      "pgfolios":{
       "value":"309a"
      }
     }
    },
    {
     "filename":"14400620.tif",
     "pagination":{
      "pgfolios":{
       "value":"309b"
      }
     }
    },
    {
     "filename":"14400621.tif",
     "pagination":{
      "pgfolios":{
       "value":"310a"
      }
     }
    },
    {
     "filename":"14400622.tif",
     "pagination":{
      "pgfolios":{
       "value":"310b"
      }
     }
    },
    {
     "filename":"14400623.tif",
     "pagination":{
      "pgfolios":{
       "value":"311a"
      }
     }
    },
    {
     "filename":"14400624.tif",
     "pagination":{
      "pgfolios":{
       "value":"311b"
      }
     }
    },
    {
     "filename":"14400625.tif",
     "pagination":{
      "pgfolios":{
       "value":"312a"
      }
     }
    },
    {
     "filename":"14400626.tif",
     "pagination":{
      "pgfolios":{
       "value":"312b"
      }
     }
    },
    {
     "filename":"14400627.tif",
     "pagination":{
      "pgfolios":{
       "value":"313a"
      }
     }
    },
    {
     "filename":"14400628.tif",
     "pagination":{
      "pgfolios":{
       "value":"313b"
      }
     }
    },
    {
     "filename":"14400629.tif",
     "pagination":{
      "pgfolios":{
       "value":"314a"
      }
     }
    },
    {
     "filename":"14400630.tif",
     "pagination":{
      "pgfolios":{
       "value":"314b"
      }
     }
    },
    {
     "filename":"14400631.tif",
     "pagination":{
      "pgfolios":{
       "value":"315a"
      }
     }
    },
    {
     "filename":"14400632.tif",
     "pagination":{
      "pgfolios":{
       "value":"315b"
      }
     }
    },
    {
     "filename":"14400633.tif",
     "pagination":{
      "pgfolios":{
       "value":"316a"
      }
     }
    },
    {
     "filename":"14400634.tif",
     "pagination":{
      "pgfolios":{
       "value":"316b"
      }
     }
    },
    {
     "filename":"14400635.tif",
     "pagination":{
      "pgfolios":{
       "value":"317a"
      }
     }
    },
    {
     "filename":"14400636.tif",
     "pagination":{
      "pgfolios":{
       "value":"317b"
      }
     }
    },
    {
     "filename":"14400637.tif",
     "pagination":{
      "pgfolios":{
       "value":"318a"
      }
     }
    },
    {
     "filename":"14400638.tif",
     "pagination":{
      "pgfolios":{
       "value":"318b"
      }
     }
    },
    {
     "filename":"14400639.tif",
     "pagination":{
      "pgfolios":{
       "value":"319a"
      }
     }
    },
    {
     "filename":"14400640.tif",
     "pagination":{
      "pgfolios":{
       "value":"319b"
      }
     }
    },
    {
     "filename":"14400641.tif",
     "pagination":{
      "pgfolios":{
       "value":"320a"
      }
     }
    },
    {
     "filename":"14400642.tif",
     "pagination":{
      "pgfolios":{
       "value":"320b"
      }
     }
    },
    {
     "filename":"14400643.tif",
     "pagination":{
      "pgfolios":{
       "value":"321a"
      }
     }
    },
    {
     "filename":"14400644.tif",
     "pagination":{
      "pgfolios":{
       "value":"321b"
      }
     }
    },
    {
     "filename":"14400645.tif",
     "pagination":{
      "pgfolios":{
       "value":"322a"
      }
     }
    },
    {
     "filename":"14400646.tif",
     "pagination":{
      "pgfolios":{
       "value":"322b"
      }
     }
    },
    {
     "filename":"14400647.tif",
     "pagination":{
      "pgfolios":{
       "value":"323a"
      }
     }
    },
    {
     "filename":"14400648.tif",
     "pagination":{
      "pgfolios":{
       "value":"323b"
      }
     }
    },
    {
     "filename":"14400649.tif",
     "pagination":{
      "pgfolios":{
       "value":"324a"
      }
     }
    },
    {
     "filename":"14400650.tif",
     "pagination":{
      "pgfolios":{
       "value":"324b"
      }
     }
    },
    {
     "filename":"14400651.tif",
     "pagination":{
      "pgfolios":{
       "value":"325a"
      }
     }
    },
    {
     "filename":"14400652.tif",
     "pagination":{
      "pgfolios":{
       "value":"325b"
      }
     }
    },
    {
     "filename":"14400653.tif",
     "pagination":{
      "pgfolios":{
       "value":"326a"
      }
     }
    },
    {
     "filename":"14400654.tif",
     "pagination":{
      "pgfolios":{
       "value":"326b"
      }
     }
    },
    {
     "filename":"14400655.tif",
     "pagination":{
      "pgfolios":{
       "value":"327a"
      }
     }
    },
    {
     "filename":"14400656.tif",
     "pagination":{
      "pgfolios":{
       "value":"327b"
      }
     }
    },
    {
     "filename":"14400657.tif",
     "pagination":{
      "pgfolios":{
       "value":"328a"
      }
     }
    },
    {
     "filename":"14400658.tif",
     "pagination":{
      "pgfolios":{
       "value":"328b"
      }
     }
    },
    {
     "filename":"14400659.tif",
     "pagination":{
      "pgfolios":{
       "value":"329a"
      }
     }
    },
    {
     "filename":"14400660.tif",
     "pagination":{
      "pgfolios":{
       "value":"329b"
      }
     }
    },
    {
     "filename":"14400661.tif",
     "pagination":{
      "pgfolios":{
       "value":"330a"
      }
     }
    },
    {
     "filename":"14400662.tif",
     "pagination":{
      "pgfolios":{
       "value":"330b"
      }
     }
    },
    {
     "filename":"14400663.tif",
     "pagination":{
      "pgfolios":{
       "value":"331a"
      }
     }
    },
    {
     "filename":"14400664.tif",
     "pagination":{
      "pgfolios":{
       "value":"331b"
      }
     }
    },
    {
     "filename":"14400665.tif",
     "pagination":{
      "pgfolios":{
       "value":"332a"
      }
     }
    },
    {
     "filename":"14400666.tif",
     "pagination":{
      "pgfolios":{
       "value":"332b"
      }
     }
    },
    {
     "filename":"14400667.tif",
     "pagination":{
      "pgfolios":{
       "value":"333a"
      }
     }
    },
    {
     "filename":"14400668.tif",
     "pagination":{
      "pgfolios":{
       "value":"333b"
      }
     }
    },
    {
     "filename":"14400669.tif",
     "pagination":{
      "pgfolios":{
       "value":"334a"
      }
     }
    },
    {
     "filename":"14400670.tif",
     "pagination":{
      "pgfolios":{
       "value":"334b"
      }
     }
    },
    {
     "filename":"14400671.tif",
     "pagination":{
      "pgfolios":{
       "value":"335a"
      }
     }
    },
    {
     "filename":"14400672.tif",
     "pagination":{
      "pgfolios":{
       "value":"335b"
      }
     }
    },
    {
     "filename":"14400673.tif",
     "pagination":{
      "pgfolios":{
       "value":"336a"
      }
     }
    },
    {
     "filename":"14400674.tif",
     "pagination":{
      "pgfolios":{
       "value":"336b"
      }
     }
    },
    {
     "filename":"14400675.tif",
     "pagination":{
      "pgfolios":{
       "value":"337a"
      }
     }
    },
    {
     "filename":"14400676.tif",
     "pagination":{
      "pgfolios":{
       "value":"337b"
      }
     }
    },
    {
     "filename":"14400677.tif",
     "pagination":{
      "pgfolios":{
       "value":"338a"
      }
     }
    },
    {
     "filename":"14400678.tif",
     "pagination":{
      "pgfolios":{
       "value":"338b"
      }
     }
    },
    {
     "filename":"14400679.tif",
     "pagination":{
      "pgfolios":{
       "value":"339a"
      }
     }
    },
    {
     "filename":"14400680.tif",
     "pagination":{
      "pgfolios":{
       "value":"339b"
      }
     }
    },
    {
     "filename":"14400681.tif",
     "pagination":{
      "pgfolios":{
       "value":"340a"
      }
     }
    },
    {
     "filename":"14400682.tif",
     "pagination":{
      "pgfolios":{
       "value":"340b"
      }
     }
    },
    {
     "filename":"14400683.tif",
     "pagination":{
      "pgfolios":{
       "value":"341a"
      }
     }
    },
    {
     "filename":"14400684.tif",
     "pagination":{
      "pgfolios":{
       "value":"341b"
      }
     }
    },
    {
     "filename":"14400685.tif",
     "pagination":{
      "pgfolios":{
       "value":"342a"
      }
     }
    },
    {
     "filename":"14400686.tif",
     "pagination":{
      "pgfolios":{
       "value":"342b"
      }
     }
    },
    {
     "filename":"14400687.tif",
     "pagination":{
      "pgfolios":{
       "value":"343a"
      }
     }
    },
    {
     "filename":"14400688.tif",
     "pagination":{
      "pgfolios":{
       "value":"343b"
      }
     }
    },
    {
     "filename":"14400689.tif",
     "pagination":{
      "pgfolios":{
       "value":"344a"
      }
     }
    },
    {
     "filename":"14400690.tif",
     "pagination":{
      "pgfolios":{
       "value":"344b"
      }
     }
    },
    {
     "filename":"14400691.tif",
     "pagination":{
      "pgfolios":{
       "value":"345a"
      }
     }
    },
    {
     "filename":"14400692.tif",
     "pagination":{
      "pgfolios":{
       "value":"345b"
      }
     }
    }
   ]
  }
 },
 "viewing-direction":"top-to-bottom"
}